Metadata-Version: 2.1
Name: hwmon
Version: 1.0
Summary: Hwmon is a collection of Python 3 scripts which are a native Python solution for obtaining information from Linux system sensors.
Home-page: https://github.com/Guillermo-C-A/Hwmon-python
Author: Guillermo-C-A & Bla6
Author-email: guillcal@ucm.es
License: gpl-3.0
Download-URL: https://github.com/bla6-apm/Hwmon-python/archive/0.9.tar.gz
Keywords: system_info,hardware_monitor,monitoring,hardware,sensors
Platform: UNKNOWN
Classifier: Development Status :: 4 - Beta
Classifier: Intended Audience :: Developers
Classifier: Operating System :: POSIX :: Linux
Classifier: Topic :: System
Classifier: Topic :: System :: Hardware
Classifier: Topic :: System :: Monitoring
Classifier: License :: OSI Approved :: GNU General Public License v3 (GPLv3)
Classifier: Programming Language :: Python :: 3
Classifier: Programming Language :: Python :: 3.6
Requires-Python: >=3.6
